nxxrdct/__init__.py
nxxrdct/utils.py
nxxrdct/version.py
nxxrdct/application/__init__.py
nxxrdct/application/nxxrdct.py
nxxrdct/nxobject/__init__.py
nxxrdct/nxobject/nxbeam.py
nxxrdct/nxobject/nxdetector.py
nxxrdct/nxobject/nxinstrument.py
nxxrdct/nxobject/nxmonitor.py
nxxrdct/nxobject/nxmonochromator.py
nxxrdct/nxobject/nxobject.py
nxxrdct/nxobject/nxsample.py
nxxrdct/nxobject/nxsource.py
nxxrdct/paths/__init__.py
nxxrdct/paths/nxxrdct.py
nxxrdct-0.1.0a0.dist-info/licenses/LICENSE
nxxrdct-0.1.0a0.dist-info/METADATA
nxxrdct-0.1.0a0.dist-info/WHEEL
nxxrdct-0.1.0a0.dist-info/top_level.txt
nxxrdct-0.1.0a0.dist-info/RECORD
