Metadata-Version: 2.4
Name: nxxrdct
Version: 0.1.0a0
Summary: Package to create, load, edit, and save files following the nxxrdct application definition.
Author-email: Pierre-Olivier Autran <pierre-olivier.autran@esrf.fr>
License: 
Project-URL: Homepage, https://github.com/nexuscontributions/nxxrdct
Project-URL: Documentation, https://nxxrdct.readthedocs.io/en/stable/
Project-URL: Repository, https://github.com/nexuscontributions/nxxrdct
Project-URL: Changelog, https://github.com/nexuscontributions/nxxrdct/-/blob/main/CHANGELOG.md
Keywords: nxxrdct,Nexus,XRD-CT,Diffraction Tomography,ESRF
Classifier: Development Status :: 3 - Alpha
Classifier: Intended Audience :: Developers
Classifier: Intended Audience :: Science/Research
Classifier: Programming Language :: Python :: 3
Classifier: Programming Language :: Python :: 3.10
Classifier: Programming Language :: Python :: 3.11
Classifier: Programming Language :: Python :: 3.12
Classifier: Programming Language :: Python :: 3.13
Classifier: Programming Language :: Python :: 3.14
Classifier: Environment :: Console
Classifier: License :: OSI Approved :: MIT License
Classifier: Operating System :: Unix
Classifier: Operating System :: MacOS :: MacOS X
Classifier: Operating System :: POSIX
Classifier: Topic :: Scientific/Engineering :: Physics
Classifier: Topic :: Scientific/Engineering :: Medical Science Apps.
Requires-Python: >=3.10
License-File: LICENSE
Requires-Dist: numpy
Requires-Dist: h5py>=3.0
Requires-Dist: silx>=2.0
Requires-Dist: pint
Requires-Dist: packaging
Provides-Extra: test
Requires-Dist: pytest; extra == "test"
Requires-Dist: black; extra == "test"
Requires-Dist: isort; extra == "test"
Requires-Dist: ruff; extra == "test"
Provides-Extra: doc
Requires-Dist: Sphinx; extra == "doc"
Requires-Dist: nbsphinx; extra == "doc"
Requires-Dist: jupyterlab; extra == "doc"
Requires-Dist: ipykernel; extra == "doc"
Requires-Dist: nbconvert; extra == "doc"
Requires-Dist: pandoc; extra == "doc"
Requires-Dist: scikit-image; extra == "doc"
Requires-Dist: h5glance; extra == "doc"
Requires-Dist: jupyter_client; extra == "doc"
Requires-Dist: pydata_sphinx_theme; extra == "doc"
Requires-Dist: sphinx_autodoc_typehints; extra == "doc"
Requires-Dist: myst-parser; extra == "doc"
Dynamic: license-file
